<?xml version='1.0'?>
<replacements xml:space='preserve' incomplete_format='false'>
<replacement offset='0' length='57'>#include &lt;iomanip>&#10;#include &lt;iostream>&#10;#include &lt;string></replacement>
<replacement offset='69' length='0'> </replacement>
<replacement offset='70' length='2'>&#10;&#10;  </replacement>
<replacement offset='74' length='0'> </replacement>
<replacement offset='93' length='1'>&#10;  </replacement>
<replacement offset='111' length='2'>&#10;  </replacement>
<replacement offset='135' length='2'>&#10;  </replacement>
<replacement offset='153' length='2'>&#10;  </replacement>
<replacement offset='168' length='3'>&#10;  </replacement>
<replacement offset='182' length='1'>&#10;  </replacement>
<replacement offset='196' length='3'>&#10;&#10;  </replacement>
<replacement offset='201' length='0'> </replacement>
<replacement offset='218' length='1'>&#10;  </replacement>
<replacement offset='231' length='0'> </replacement>
<replacement offset='258' length='1'>&#10;  </replacement>
<replacement offset='281' length='1'>&#10;  </replacement>
<replacement offset='294' length='0'> </replacement>
<replacement offset='326' length='1'>&#10;  </replacement>
<replacement offset='354' length='2'>&#10;  </replacement>
<replacement offset='390' length='1'>&#10;  </replacement>
<replacement offset='415' length='3'>&#10;&#10;  </replacement>
<replacement offset='420' length='0'> </replacement>
<replacement offset='429' length='2'>&#10;  </replacement>
<replacement offset='452' length='2'>&#10;  </replacement>
<replacement offset='469' length='0'> </replacement>
<replacement offset='470' length='0'> </replacement>
<replacement offset='480' length='1'>&#10;  </replacement>
<replacement offset='486' length='2'> </replacement>
<replacement offset='497' length='0'> </replacement>
<replacement offset='498' length='0'> </replacement>
<replacement offset='513' length='0'> </replacement>
<replacement offset='514' length='0'> </replacement>
<replacement offset='519' length='1'>&#10;  </replacement>
<replacement offset='551' length='2'>&#10;&#10;  </replacement>
<replacement offset='555' length='0'> </replacement>
<replacement offset='575' length='1'>&#10;  </replacement>
<replacement offset='593' length='1'>&#10;            </replacement>
<replacement offset='596' length='0'> </replacement>
<replacement offset='613' length='1'>&#10;            </replacement>
<replacement offset='621' length='1'>&#10;            </replacement>
<replacement offset='624' length='0'> </replacement>
<replacement offset='646' length='1'>&#10;            </replacement>
<replacement offset='654' length='2'>&#10;            </replacement>
<replacement offset='658' length='0'> </replacement>
<replacement offset='691' length='3'>&#10;            </replacement>
<replacement offset='696' length='0'> </replacement>
<replacement offset='723' length='2'>&#10;            </replacement>
<replacement offset='727' length='0'> </replacement>
<replacement offset='745' length='0'> </replacement>
<replacement offset='749' length='2'>&#10;            </replacement>
<replacement offset='753' length='0'> </replacement>
<replacement offset='775' length='1'>&#10;            </replacement>
<replacement offset='783' length='2'>&#10;            </replacement>
<replacement offset='787' length='0'> </replacement>
<replacement offset='815' length='3'>&#10;&#10;  </replacement>
</replacements>
